{
  "ar_id": "114",
  "validation_command": "python temp/validate_ar114.py",
  "run_count": 3,
  "runs": [
    {
      "run": 1,
      "exit_code": 0,
      "hash_full": "ef39b9fa766255a1b9ee81a33eb5afe13fb2f5ec5ace350e3dc304a04930074e",
      "hash": "ef39b9fa766255a1",
      "stdout_len": 76,
      "stderr_len": 0
    },
    {
      "run": 2,
      "exit_code": 0,
      "hash_full": "ef39b9fa766255a1b9ee81a33eb5afe13fb2f5ec5ace350e3dc304a04930074e",
      "hash": "ef39b9fa766255a1",
      "stdout_len": 76,
      "stderr_len": 0
    },
    {
      "run": 3,
      "exit_code": 0,
      "hash_full": "ef39b9fa766255a1b9ee81a33eb5afe13fb2f5ec5ace350e3dc304a04930074e",
      "hash": "ef39b9fa766255a1",
      "stdout_len": 76,
      "stderr_len": 0
    }
  ],
  "triple_consistency": "OK",
  "testador_exit_code": 0,
  "executor_exit_code": 0,
  "consistency": "OK",
  "status": "SUCESSO",
  "ah_flags": [],
  "evidence_pack_complete": true,
  "rejection_reason": null,
  "workspace_clean": true
}