{
  "ar_id": "224",
  "validation_command": "cd \"Hb Track - Backend\" && pytest tests/training/contracts/test_contract_train_097_100_presence_pending.py -v --tb=short 2>&1",
  "run_count": 3,
  "runs": [
    {
      "run": 1,
      "exit_code": 0,
      "hash_full": "e6c3e5ac5fee5aaae975740e15f7665448df363405de36f3dc8081c26970a0e0",
      "hash": "e6c3e5ac5fee5aaa",
      "stdout_len": 18072,
      "stderr_len": 0
    },
    {
      "run": 2,
      "exit_code": 0,
      "hash_full": "e6c3e5ac5fee5aaae975740e15f7665448df363405de36f3dc8081c26970a0e0",
      "hash": "e6c3e5ac5fee5aaa",
      "stdout_len": 18072,
      "stderr_len": 0
    },
    {
      "run": 3,
      "exit_code": 0,
      "hash_full": "e6c3e5ac5fee5aaae975740e15f7665448df363405de36f3dc8081c26970a0e0",
      "hash": "e6c3e5ac5fee5aaa",
      "stdout_len": 18072,
      "stderr_len": 0
    }
  ],
  "triple_consistency": "OK",
  "testador_exit_code": 0,
  "executor_exit_code": 0,
  "consistency": "OK",
  "status": "SUCESSO",
  "ah_flags": [],
  "evidence_pack_complete": true,
  "rejection_reason": null,
  "workspace_clean": true
}